ialgebra/__init__.py
ialgebra/interpreters/GuidedBackpropGrad.py
ialgebra/interpreters/GuidedBackpropSmoothGrad.py
ialgebra/interpreters/__init__.py
ialgebra/interpreters/gradcam.py
ialgebra/interpreters/gradsaliency.py
ialgebra/interpreters/interpreter.py
ialgebra/interpreters/mask.py
ialgebra/interpreters/smoothgrad.py
ialgebra/models/__init__.py
ialgebra/models/densenet.py
ialgebra/models/lenet.py
ialgebra/models/model.py
ialgebra/models/resnet.py
ialgebra/models/vgg.py
ialgebra/operations/__init__.py
ialgebra/operations/compositer.py
ialgebra/operations/operator.py
ialgebra/utils/__init__.py
ialgebra/utils/utils_data.py
ialgebra/utils/utils_interpreter.py
ialgebra/utils/utils_main.py
ialgebra/utils/utils_model.py
ialgebra/utils/utils_operation.py
pytorch_ialgebra-1.0.1.dist-info/LICENSE.txt
pytorch_ialgebra-1.0.1.dist-info/METADATA
pytorch_ialgebra-1.0.1.dist-info/WHEEL
pytorch_ialgebra-1.0.1.dist-info/entry_points.txt
pytorch_ialgebra-1.0.1.dist-info/top_level.txt
pytorch_ialgebra-1.0.1.dist-info/RECORD
